{"version":1,"functions":{"/api/admin/reviews":{},"/api/admin/ads":{},"/api/admin/blog":{},"/api/admin/blog/[id]":{},"/api/admin/settings":{},"/api/admin/shops/[id]/feature":{},"/api/ads/[slot]":{},"/api/admin/shops":{},"/api/admin/shops/import":{},"/api/admin/sponsors/[id]/toggle":{},"/api/admin/shops/[id]":{},"/opengraph-image":{},"/sitemap.xml":{},"/api/admin/shops/google-search":{},"/aanmelden":{},"/[category]":{},"/admin/blog":{},"/[category]/[location]":{},"/admin/reviews":{},"/admin":{},"/admin/shops":{},"/_not-found":{},"/blog":{},"/faq":{},"/blog/[slug]":{},"/gebruiksvoorwaarden":{},"/gratis-aanmelden":{},"/api/admin/sponsors":{},"/modest-fashion/[land]":{},"/":{},"/over-ons":{},"/verify/[token]":{},"/privacybeleid":{},"/shops":{},"/shops/[slug]":{}}}