{"version":1,"functions":{"/api/admin/blog":{},"/api/admin/settings":{},"/api/admin/ads":{},"/api/admin/blog/[id]":{},"/api/admin/reviews":{},"/api/admin/shops/[id]/feature":{},"/api/admin/shops/google-search":{},"/api/admin/shops":{},"/api/admin/sponsors/[id]/toggle":{},"/api/ads/[slot]":{},"/api/admin/sponsors":{},"/api/admin/shops/import":{},"/opengraph-image":{},"/aanmelden":{},"/sitemap.xml":{},"/[category]":{},"/admin/blog":{},"/[category]/[location]":{},"/admin":{},"/admin/reviews":{},"/admin/shops":{},"/faq":{},"/blog/[slug]":{},"/gebruiksvoorwaarden":{},"/gratis-aanmelden":{},"/blog":{},"/over-ons":{},"/modest-fashion/[land]":{},"/privacybeleid":{},"/":{},"/shops":{},"/verify/[token]":{},"/shops/[slug]":{},"/api/admin/shops/[id]":{},"/_not-found":{}}}